laconiq/__init__.py
laconiq/generators.py
laconiq/maker.py
laconiq-0.3.0.dist-info/LICENSE
laconiq-0.3.0.dist-info/METADATA
laconiq-0.3.0.dist-info/WHEEL
laconiq-0.3.0.dist-info/RECORD
