Metadata-Version: 2.1
Name: laconiq
Version: 0.3.0
Summary: 
Author: Eugen Ciur
Author-email: eugen@papermerge.com
Requires-Python: >=3.10,<4.0
Classifier: Programming Language :: Python :: 3
Classifier: Programming Language :: Python :: 3.10
Classifier: Programming Language :: Python :: 3.11
Classifier: Programming Language :: Python :: 3.12
Requires-Dist: pydantic[email] (>=2.5,<3.0)
